pix/__init__.py
pix/cli_parser.py
pix/converter.py
pix/croper.py
pix/main.py
pix/manifest.json
pix/prune.py
pix/resizer.py
pix/utils.py
zz_pix-0.0.9.dist-info/LICENSE
zz_pix-0.0.9.dist-info/METADATA
zz_pix-0.0.9.dist-info/WHEEL
zz_pix-0.0.9.dist-info/entry_points.txt
zz_pix-0.0.9.dist-info/top_level.txt
zz_pix-0.0.9.dist-info/RECORD
