Metadata-Version: 2.1
Name: zz-pix
Version: 0.0.9
Summary: CLI tool for image manipulation
Home-page: https://github.com/sean1832/pix
Author: Zeke Zhang
Classifier: Development Status :: 1 - Planning
Classifier: Environment :: Console
Classifier: Intended Audience :: End Users/Desktop
Classifier: License :: OSI Approved :: Apache Software License
Classifier: Operating System :: OS Independent
Classifier: Programming Language :: Python :: 3
Classifier: Programming Language :: Python :: 3 :: Only
Classifier: Programming Language :: Python :: 3.9
Classifier: Programming Language :: Python :: 3.10
Classifier: Programming Language :: Python :: 3.11
Classifier: Programming Language :: Python :: 3.12
Classifier: Topic :: Multimedia :: Graphics
Classifier: Topic :: Multimedia :: Graphics :: Graphics Conversion
Classifier: Topic :: Multimedia :: Graphics :: Editors
Classifier: Topic :: Multimedia :: Graphics :: Editors :: Raster-Based
Requires-Python: >=3.9
License-File: LICENSE
Requires-Dist: pillow
Requires-Dist: pillow-avif-plugin
Requires-Dist: pillow-heif
Requires-Dist: termcolor
Requires-Dist: tqdm
